README.md
setup.py
papertrail_cli.egg-info/PKG-INFO
papertrail_cli.egg-info/SOURCES.txt
papertrail_cli.egg-info/dependency_links.txt
papertrail_cli.egg-info/entry_points.txt
papertrail_cli.egg-info/pbr.json
papertrail_cli.egg-info/requires.txt
papertrail_cli.egg-info/top_level.txt
pt/__init__.py
pt/client.py
pt/pql.py
pt/pt.py
pt/service.py
pt/utils.py
pt/version.py
pt/commands/__init__.py
pt/commands/build.py
pt/commands/docker.py
pt/commands/test.py
pt/commands/upgrade.py