Metadata-Version: 1.0
Name: papertrail-cli
Version: 1.1.58
Summary: Papertrail Command Line Utils
Home-page: https://github.com/egis/papertrail-python-cli
Author: Egis Software
Author-email: UNKNOWN
License: UNKNOWN
Platform: UNKNOWN
